promptplayground/PromptPlayground.py
promptplayground/__init__.py
promptplayground-0.0.1.dist-info/METADATA
promptplayground-0.0.1.dist-info/WHEEL
promptplayground-0.0.1.dist-info/RECORD
